RobotRequirementsCovarege/__init__.py
RobotRequirementsCovarege/coverage_template.py
robotframework_reqcov-0.1.3.dist-info/METADATA
robotframework_reqcov-0.1.3.dist-info/WHEEL
robotframework_reqcov-0.1.3.dist-info/RECORD
