Metadata-Version: 2.1
Name: robotframework-reqcov
Version: 0.1.3
Summary: Listener for generating requirement coverage reports for tests performed with Robot Framework
License: License :: OSI Approved :: Apache Software License
Author: Robot Courses
Author-email: git@robotcourses.com.br
Requires-Python: >=3.8,<4.0
Classifier: Development Status :: 5 - Production/Stable
Classifier: Framework :: Robot Framework
Classifier: Framework :: Robot Framework :: Library
Classifier: License :: Other/Proprietary License
Classifier: Operating System :: OS Independent
Classifier: Programming Language :: Python
Classifier: Programming Language :: Python :: 3
Classifier: Programming Language :: Python :: 3.8
Classifier: Programming Language :: Python :: 3.9
Classifier: Programming Language :: Python :: 3.10
Classifier: Programming Language :: Python :: 3.11
Classifier: Programming Language :: Python :: 3.12
Classifier: Programming Language :: Python :: 3.13
Classifier: Topic :: Software Development :: Quality Assurance
Classifier: Topic :: Software Development :: Testing
Requires-Dist: robotframework (>=7.0,<8.0)
Project-URL: Bugs Tracker, https://github.com/robotcourses/robotframework-reqcov/issues
Project-URL: Github, https://github.com/robotcourses/robotframework-reqcov
